letta_evals/__init__.py
letta_evals/cli.py
letta_evals/constants.py
letta_evals/decorators.py
letta_evals/models.py
letta_evals/py.typed
letta_evals/runner.py
letta_evals/streaming.py
letta_evals/types.py
letta_evals/utils.py
letta_evals/datasets/__init__.py
letta_evals/datasets/loader.py
letta_evals/extractors/__init__.py
letta_evals/extractors/builtin.py
letta_evals/extractors/registry.py
letta_evals/extractors/utils.py
letta_evals/graders/__init__.py
letta_evals/graders/agent_judge.py
letta_evals/graders/base.py
letta_evals/graders/builtin.py
letta_evals/graders/prompt_utils.py
letta_evals/graders/rubric.py
letta_evals/graders/tool.py
letta_evals/llm_model_configs/azure-gpt-4o-mini.json
letta_evals/llm_model_configs/claude-3-5-haiku.json
letta_evals/llm_model_configs/claude-3-7-sonnet-extended.json
letta_evals/llm_model_configs/claude-3-7-sonnet.json
letta_evals/llm_model_configs/claude-4-1-opus.json
letta_evals/llm_model_configs/claude-4-5-haiku.json
letta_evals/llm_model_configs/claude-4-5-opus.json
letta_evals/llm_model_configs/claude-4-5-sonnet.json
letta_evals/llm_model_configs/claude-4-sonnet-extended.json
letta_evals/llm_model_configs/claude-4-sonnet.json
letta_evals/llm_model_configs/deepseek-chat.json
letta_evals/llm_model_configs/deepseek-reasoner.json
letta_evals/llm_model_configs/gemini-2-5-flash-0925.json
letta_evals/llm_model_configs/gemini-2-5-flash.json
letta_evals/llm_model_configs/gemini-2-5-pro.json
letta_evals/llm_model_configs/gemini-3-flash.json
letta_evals/llm_model_configs/gemini-3-pro.json
letta_evals/llm_model_configs/gemini-vertex.json
letta_evals/llm_model_configs/groq.json
letta_evals/llm_model_configs/letta-hosted.json
letta_evals/llm_model_configs/ollama.json
letta_evals/llm_model_configs/openai-gpt-3.5-turbo.json
letta_evals/llm_model_configs/openai-gpt-4.1-mini.json
letta_evals/llm_model_configs/openai-gpt-4.1-nano.json
letta_evals/llm_model_configs/openai-gpt-4.1.json
letta_evals/llm_model_configs/openai-gpt-4o-mini.json
letta_evals-0.9.0.dist-info/METADATA
letta_evals-0.9.0.dist-info/WHEEL
letta_evals-0.9.0.dist-info/entry_points.txt
letta_evals-0.9.0.dist-info/licenses/LICENSE
letta_evals-0.9.0.dist-info/RECORD
