Metadata-Version: 2.4
Name: letta-evals
Version: 0.9.0
Summary: Evaluation framework for Letta AI agents
Project-URL: Homepage, https://github.com/letta-ai/letta-evals-kit
Project-URL: Repository, https://github.com/letta-ai/letta-evals-kit
Project-URL: Issues, https://github.com/letta-ai/letta-evals-kit/issues
Author-email: Letta AI <contact@letta.com>
License: Apache-2.0
License-File: LICENSE
Classifier: Development Status :: 4 - Beta
Classifier: Intended Audience :: Developers
Classifier: License :: OSI Approved :: Apache Software License
Classifier: Natural Language :: English
Classifier: Operating System :: OS Independent
Classifier: Programming Language :: Python
Classifier: Programming Language :: Python :: 3
Classifier: Programming Language :: Python :: 3 :: Only
Classifier: Programming Language :: Python :: 3.11
Classifier: Programming Language :: Python :: 3.12
Classifier: Programming Language :: Python :: 3.13
Classifier: Topic :: Scientific/Engineering :: Artificial Intelligence
Classifier: Topic :: Software Development :: Testing
Requires-Python: <3.14,>=3.11
Requires-Dist: anthropic>=0.71.0
Requires-Dist: anyio==4.10.0
Requires-Dist: jinja2>=3.1.0
Requires-Dist: jsonpath-ng>=1.6.0
Requires-Dist: letta-client>=1.0.0
Requires-Dist: matplotlib>=3.10.6
Requires-Dist: openai>=1.0.0
Requires-Dist: pandas>=2.3.2
Requires-Dist: pathspec>=0.12.1
Requires-Dist: pydantic>=2.0.0
Requires-Dist: python-dotenv>=1.0.0
Requires-Dist: pyyaml>=6.0
Requires-Dist: rich>=13.0.0
Requires-Dist: typer>=0.12.0
Provides-Extra: dev
Requires-Dist: pre-commit>=3.0.0; extra == 'dev'
Requires-Dist: pytest-asyncio>=0.23.0; extra == 'dev'
Requires-Dist: pytest>=8.0.0; extra == 'dev'
Requires-Dist: ruff>=0.6.0; extra == 'dev'
Provides-Extra: filesystem
Requires-Dist: faker>=37.6.0; extra == 'filesystem'
Provides-Extra: skills
Requires-Dist: openpyxl>=3.1.5; extra == 'skills'
Requires-Dist: pathspec>=0.12.1; extra == 'skills'
Requires-Dist: xlrd>=2.0.2; extra == 'skills'
